{"total":28,"rows":[
	{"OptionNumber":"5","voteNumber":5,"voteTitle":"选出你心中最好的下载工具"},
	{"OptionNumber":"12","voteNumber":1,"voteTitle":"选出你心中最好的输入法"},
	{"OptionNumber":"10","voteNumber":3,"voteTitle":"选出你心中最好的浏览器"},
	{"OptionNumber":"4","voteNumber":2,"voteTitle":"选出你心中最好的社交软件"},
	{"OptionNumber":"3","voteNumber":3,"voteTitle":"选出你心中最好的杀毒软件"},
	{"OptionNumber":"11","voteNumber":1,"voteTitle":"选出你心中最好的聊天工具"},
	{"OptionNumber":"21","voteNumber":8,"voteTitle":"选出你心中最好的翻译软件"},
	{"OptionNumber":"20","voteNumber":2,"voteTitle":"选出你心中最好的免费软件"},
	{"OptionNumber":"12","voteNumber":8,"voteTitle":"选出你心中最好的录音软件"},
	{"OptionNumber":"31","voteNumber":6,"voteTitle":"选出你心中最好的播放器"},
	{"OptionNumber":"22","voteNumber":5,"voteTitle":"选出你心中最好的刷机软件"}
]}
